minibump/__init__.py
minibump/main.py
minibump-0.0.2.dist-info/LICENCE.md
minibump-0.0.2.dist-info/METADATA
minibump-0.0.2.dist-info/WHEEL
minibump-0.0.2.dist-info/entry_points.txt
minibump-0.0.2.dist-info/top_level.txt
minibump-0.0.2.dist-info/RECORD
