Metadata-Version: 2.1
Name: minibump
Version: 0.0.2
Summary: Bump versions in changelogs and pyprojects
Author-email: Loïc Grobol <loic.grobol@gmail.com>
License: MIT
Project-URL: Bug Tracker, https://github.com/loicgrobol/minibump/issues
Project-URL: Changes, https://github.com/loicgrobol/minibump/blob/main/CHANGELOG.md
Project-URL: Documentation, https://github.com/loicgrobol/minibump/blob/main/README.md
Project-URL: Source Code, https://github.com/loicgrobol/minibump
Classifier: License :: OSI Approved :: MIT License
Classifier: Programming Language :: Python :: 3.10
Requires-Python: >=3.10
License-File: LICENCE.md
Requires-Dist: click (>=8)
Requires-Dist: keepachangelog
Requires-Dist: semver (>=2.10)
Requires-Dist: temppathlib
Requires-Dist: tomlkit
Provides-Extra: lint
Requires-Dist: black ; extra == 'lint'
Requires-Dist: flake8-bugbear ; extra == 'lint'
Requires-Dist: flake8-pyproject ; extra == 'lint'
Requires-Dist: flake8-pytest-style ; extra == 'lint'
Requires-Dist: mypy ; extra == 'lint'
Provides-Extra: tests
Requires-Dist: freezegun (>=1) ; extra == 'tests'
Requires-Dist: pytest ; extra == 'tests'
Requires-Dist: pytest-console-scripts ; extra == 'tests'
Requires-Dist: pytest-datadir ; extra == 'tests'
